voidapi/__init__.py
voidapi/main.py
voidapi-1.1.0.dist-info/METADATA
voidapi-1.1.0.dist-info/WHEEL
voidapi-1.1.0.dist-info/top_level.txt
voidapi-1.1.0.dist-info/RECORD
