Metadata-Version: 2.1
Name: voidapi
Version: 1.1.0
Summary: A simple API wrapper for voidbots.net.
Home-page: https://github.com/ggashish/voidapi
Author: Ashish Yadav
Author-email: ashugodhai@gmail.com
License: MIT
Keywords: void,voidbots.net
Platform: UNKNOWN
Classifier: Development Status :: 5 - Production/Stable
Classifier: License :: OSI Approved :: MIT License
Classifier: Programming Language :: Python :: 3
Classifier: Programming Language :: Python :: 3.6
Classifier: Programming Language :: Python :: 3.7
Classifier: Programming Language :: Python :: 3.8
Requires-Dist: aiohttp
Requires-Dist: discord.py
Requires-Dist: python-dateutil
